unitycatalog_client/__init__.py
unitycatalog_client/api/__init__.py
unitycatalog_client/api/catalogs_api.py
unitycatalog_client/api/functions_api.py
unitycatalog_client/api/grants_api.py
unitycatalog_client/api/model_versions_api.py
unitycatalog_client/api/registered_models_api.py
unitycatalog_client/api/schemas_api.py
unitycatalog_client/api/tables_api.py
unitycatalog_client/api/temporary_credentials_api.py
unitycatalog_client/api/volumes_api.py
unitycatalog_client/api_client.py
unitycatalog_client/api_response.py
unitycatalog_client/configuration.py
unitycatalog_client/exceptions.py
unitycatalog_client/models/__init__.py
unitycatalog_client/models/aws_credentials.py
unitycatalog_client/models/azure_user_delegation_sas.py
unitycatalog_client/models/catalog_info.py
unitycatalog_client/models/column_info.py
unitycatalog_client/models/column_type_name.py
unitycatalog_client/models/create_catalog.py
unitycatalog_client/models/create_function.py
unitycatalog_client/models/create_function_request.py
unitycatalog_client/models/create_model_version.py
unitycatalog_client/models/create_registered_model.py
unitycatalog_client/models/create_schema.py
unitycatalog_client/models/create_table.py
unitycatalog_client/models/create_volume_request_content.py
unitycatalog_client/models/data_source_format.py
unitycatalog_client/models/dependency.py
unitycatalog_client/models/dependency_list.py
unitycatalog_client/models/finalize_model_version.py
unitycatalog_client/models/function_dependency.py
unitycatalog_client/models/function_info.py
unitycatalog_client/models/function_parameter_info.py
unitycatalog_client/models/function_parameter_infos.py
unitycatalog_client/models/function_parameter_mode.py
unitycatalog_client/models/function_parameter_type.py
unitycatalog_client/models/gcp_oauth_token.py
unitycatalog_client/models/generate_temporary_model_version_credential.py
unitycatalog_client/models/generate_temporary_path_credential.py
unitycatalog_client-1.0.0.dist-info/METADATA
unitycatalog_client-1.0.0.dist-info/WHEEL
unitycatalog_client-1.0.0.dist-info/RECORD
